{"name":"Add a new pet for owner","testSteps":[{"number":1,"description":"[1] {identifier\u003d1, name\u003d\"Dolly\", type\u003d\"1\"}","duration":13593,"startTime":1471449040284,"screenshots":[{"screenshot":"a19619efba2a3457101317bbdcce2bb7.png"}],"result":"SUCCESS","children":[{"number":2,"description":"Given a registered user","duration":8408,"startTime":1471449040297,"screenshots":[{"screenshot":"3a4cbf3c6f5710fed06cd8ea4caa4f60.png"}],"result":"SUCCESS"},{"number":3,"description":"And owner with 1","duration":843,"startTime":1471449048707,"screenshots":[{"screenshot":"3a4cbf3c6f5710fed06cd8ea4caa4f60.png"},{"screenshot":"296514c4edd26634e9be559e3da43f0e.png"}],"result":"SUCCESS"},{"number":4,"description":"When add a new pet with \"Dolly\" and \"1\" agaisnt an owner","duration":3514,"startTime":1471449049551,"screenshots":[{"screenshot":"1e806b1dc71b39479320c82d99296a86.png"},{"screenshot":"e6bc82312ebadb79614850d301efaf1c.png"}],"result":"SUCCESS"},{"number":5,"description":"Then I shoud be able to see it under same owner 1 profile with same \"Dolly\" and \"1\"","duration":565,"startTime":1471449053066,"screenshots":[{"screenshot":"a19619efba2a3457101317bbdcce2bb7.png"}],"result":"SUCCESS"}]},{"number":6,"description":"[1] {identifier\u003d1, name\u003d\"Shadow\", type\u003d\"2\"}","duration":7589,"startTime":1471449056151,"screenshots":[{"screenshot":"12e8fff38911bd289512d8f622d1c9eb.png"}],"result":"SUCCESS","children":[{"number":7,"description":"Given a registered user","duration":2991,"startTime":1471449056153,"screenshots":[{"screenshot":"98ab8af95b3a1f1766fc9ebecf7dafd1.png"}],"result":"SUCCESS"},{"number":8,"description":"And owner with 1","duration":705,"startTime":1471449059144,"screenshots":[{"screenshot":"3a4cbf3c6f5710fed06cd8ea4caa4f60.png"},{"screenshot":"13b22e01dbdf3f5ec52089b9ee878c16.png"}],"result":"SUCCESS"},{"number":9,"description":"When add a new pet with \"Shadow\" and \"2\" agaisnt an owner","duration":3075,"startTime":1471449059849,"screenshots":[{"screenshot":"b9d8da2516e3478cb3182ab9fe10b1a0.png"},{"screenshot":"e105ec280e3b686ec19c2af71d556c19.png"}],"result":"SUCCESS"},{"number":10,"description":"Then I shoud be able to see it under same owner 1 profile with same \"Shadow\" and \"2\"","duration":528,"startTime":1471449062924,"screenshots":[{"screenshot":"12e8fff38911bd289512d8f622d1c9eb.png"}],"result":"SUCCESS"}]}],"userStory":{"id":"add-or-update-pet-information.","storyName":"Add or update pet information.","path":"add_or_update_pet/new_pet.feature","type":"feature"},"title":"Add a new pet for owner","description":"","tags":[{"name":"Add or update pet","type":"capability"},{"name":"Add or update pet/Add or update pet information.","type":"feature"}],"startTime":1471449040166,"duration":23575,"driver":"provided","dataTable":{"headers":["identifier","name","type"],"rows":[{"values":["1","\"Dolly\"","\"1\""],"result":"SUCCESS"},{"values":["1","\"Shadow\"","\"2\""],"result":"SUCCESS"}],"predefinedRows":true,"currentRow":{"value":1},"dataSetDescriptors":[{"startRow":0,"rowCount":0,"name":"","description":""}]},"manual":false,"result":"SUCCESS"}